nest_server/__init__.py
nest_server/app.py
nest_server/main.py
nest_server/api/__init__.py
nest_server/api/client.py
nest_server/api/decorator.py
nest_server/api/initializer.py
nest_server/api/normalizer.py
nest_server/exec/__init__.py
nest_server/exec/helpers.py
nest_server/scripts/__init__.py
nest_server/scripts/converter.py
nest_server/scripts/model.py
nest_server/scripts/restriction.py
nest_server/scripts/serialize.py
nest_server/scripts/simulation.py
nest_server-2.5.1.data/scripts/nest-server
nest_server-2.5.1.dist-info/LICENSE
nest_server-2.5.1.dist-info/METADATA
nest_server-2.5.1.dist-info/WHEEL
nest_server-2.5.1.dist-info/top_level.txt
nest_server-2.5.1.dist-info/RECORD
