Metadata-Version: 2.1
Name: nest-server
Version: 2.5.1
Summary: A server for NEST Simulator with REST API
Home-page: https://github.com/babsey/nest-server
License: MIT License
Platform: UNKNOWN
Classifier: License :: OSI Approved :: MIT License
Classifier: Operating System :: OS Independent
Classifier: Programming Language :: Python :: 3
Requires-Python: >=3.6
Requires-Dist: flask
Requires-Dist: flask-cors
Requires-Dist: nestml
Requires-Dist: numpy
Requires-Dist: RestrictedPython
Requires-Dist: uwsgi
